register_xfer/register_xfer.v
// WIDTH_AX must be 2x WIDTH_MAIN
module register_xfer #(
    parameter DEFAULT_VALUE = 0, // defaults to zero
    parameter WIDTH_AX = 16, // bus width for addr and xfer bus in bits
    parameter WIDTH_MAIN = 8 // bus width for main bus in bits
) (
    input clk,

    // address bus
    input [WIDTH_AX-1:0] addr_in,
    input assert_addr,
    output [WIDTH_AX-1:0] addr_out,
    output addr_en,

    // xfer bus
    input [WIDTH_AX-1:0] xfer_in,
    input assert_xfer, load_xfer,
    output [WIDTH_AX-1:0] xfer_out,
    output xfer_en,

    // main bus
    input [WIDTH_MAIN-1:0] main_in,
    input assertlow_main, asserthigh_main, loadlow_main, loadhigh_main,
    output [WIDTH_MAIN-1:0] main_out,
    output main_en
);
    reg [WIDTH_AX-1:0] value = DEFAULT_VALUE;

    // do everything at a clock edge to make timing more predictable
    always @(posedge clk) begin
        value <= !load_xfer ? xfer_in :   // load xfer
                !loadlow_main ? {value[WIDTH_AX-1:WIDTH_AX-WIDTH_MAIN], main_in[WIDTH_MAIN-1:0]} : // load main to low
                !loadhigh_main ? {main_in[WIDTH_MAIN-1:0], value[WIDTH_MAIN-1:0]} : // load main to high
                value;                  // no change
    end

    // note that the bus takes care enable behavior, so we just output the data at all times
    assign addr_out = value;
    assign addr_en = ~assert_addr;

    assign xfer_out = value;
    assign xfer_en = ~assert_xfer;

    // slightly weird to only use the assertlow to determine which output goes to main, but the bus handles the rest
    assign main_out = assertlow_main ? value[WIDTH_AX-1:WIDTH_AX-WIDTH_MAIN] : value[WIDTH_MAIN:0];
    // bus enable is active high, asserts are active low
    assign main_en = ~(assertlow_main & asserthigh_main);

endmodule

register_xfer/register_xfer_tb.sv
`timescale 1ns/1ps 
module register_xfer_tb();
    localparam WIDTH_AX = 16; // bus width for addr and xfer bus in bits
    localparam WIDTH_MAIN = 8; // bus width for main bus in bits

	reg clk = 0;
    reg reset = 0;
    reg [WIDTH_AX-1:0] bus_in_addr = 16'hAAAA;
    reg [WIDTH_AX-1:0] bus_in_xfer = 16'h5555;
    reg [WIDTH_MAIN-1:0] bus_in_main = 8'h00;
    reg assert_addr = 1'b1;
    reg assert_xfer = 1'b1;
    reg load_xfer = 1'b1;

    reg assertlow_main = 1'b1;
    reg asserthigh_main = 1'b1;
    reg loadlow_main = 1'b1;
    reg loadhigh_main = 1'b1;

    wire [WIDTH_AX-1:0] addr_out;
    wire [WIDTH_AX-1:0] xfer_out;
    wire [WIDTH_MAIN-1:0] main_out;

    wire addr_en, xfer_en, main_en;

    // #(.WIDTH_AX(16), .WIDTH_MAIN(8))
    register_xfer  register_xfer1 (
        .clk(clk),
        .addr_in(bus_in_addr),
        .xfer_in(bus_in_xfer),
        .main_in(bus_in_main),
        .assert_addr(assert_addr),
        .assert_xfer(assert_xfer),
        .assertlow_main(assertlow_main),
        .asserthigh_main(asserthigh_main),
        .load_xfer(load_xfer),
        .loadlow_main(loadlow_main),
        .loadhigh_main(loadhigh_main),
        .addr_out(addr_out),
        .xfer_out(xfer_out),
        .main_out(main_out),
        .addr_en(addr_en),
        .xfer_en(xfer_en),
        .main_en(main_en)
    );
	
    // bus #(.WIDTH(8),.COUNT(4)) top1 (.clk(clk), .in({bus_in_a,bus_in_b,bus_in_c,bus_in_d}),.enable(en_in));

	always
		#(5) clk <= !clk;

	initial
	begin
		$display("test");
		$dumpfile("register_xfer_tb.vcd");
		$dumpvars(0,register_xfer_tb);
        #5


        // default to no outputs
        #0 assert (main_en == 1'b0) 
            $display ("main_en: no asserts OK");
            else $error("main_en: no asserts NOT OK");
        #0 assert (addr_en == 1'b0) 
            $display ("addr_en: no asserts OK");
            else $error("addr_en: no asserts NOT OK");
        #0 assert (xfer_en == 1'b0) 
            $display ("xfer_en: no asserts OK");
            else $error("xfer_en: no asserts NOT OK");

        // assert xfer to check initial value
        #10 assert_xfer = 1'b0;
        #0 assert (xfer_out == 16'h0000)
            $display ("init: value = 0 OK");
            else $error("init: value = 0 NOT OK");
        #0 assert (xfer_en == 1'b1) 
            $display ("xfer_en: assert_xfer OK");
            else $error("xfer_en: assert_xfer NOT OK");
        #10 assert_xfer = 1'b1;

        // load xfer
		#10 load_xfer = 1'b0;
        #10 load_xfer = 1'b1;

        // assert xfer to check value after load xfer
        #10 assert_xfer = 1'b0;
        #0 assert (xfer_out == 16'h5555)
            $display ("load_xfer: value = 16'h5555 OK");
            else $error("load_xfer: value = 16'h5555 NOT OK");
        #10 assert_xfer = 1'b1;


        // load main high
        #10 loadhigh_main = 1'b0;
        #10 loadhigh_main = 1'b1;

        // assert xfer to check value after loadhigh_main
        #10 assert_xfer = 1'b0;
        #0 assert (xfer_out == 16'h0055)
            $display ("loadhigh_main: value = 16'h0055 OK");
            else $error("loadhigh_main: value = 16'h0055 NOT OK");
        #10 assert_xfer = 1'b1;

        // assert addr
        #10 assert_addr = 1'b0;
        #0 assert (addr_out == 16'h0055)
            $display ("assert_addr: value = 16'h0055 OK");
            else $error("assert_addr: value = 16'h0055 NOT OK");
        #0 assert (addr_en == 1'b1) 
            $display ("addr_en: assert_addr OK");
            else $error("addr_en: assert_addr NOT OK");
        #10 assert_addr = 1'b1;

        // assert low to main
        #10 assertlow_main = 1'b0;
        #0 assert (main_en == 1'b1) 
            $display ("assertlow_main: main_en OK");
            else $error("assertlow_main: main_en NOT OK");
        #0 assert (main_out == 8'h55)
            $display ("assertlow_main: value = 8'h55 OK");
            else $error("assertlow_main: value = 8'h55 NOT OK");
        #10 assertlow_main = 1'b1;


        // assert high to main
        #10 asserthigh_main = 1'b0;
        #0 assert (main_en == 1'b1) 
            $display ("asserthigh_main: main_en OK");
            else $error("asserthigh_main: main_en NOT OK");
        #0 assert (main_out == 8'h00)
            $display ("asserthigh_main: value = 8'h00 OK");
            else $error("asserthigh_main: value = 8'h00 NOT OK");
        #10 asserthigh_main = 1'b1;

        #10 $finish;
	end
endmodule

build/tests/register_xfer_tb.vcd
$date
	Thu May  6 11:04:33 2021
$end
$version
	Icarus Verilog
$end
$timescale
	1ps
$end
$scope module register_xfer_tb $end
$var wire 16 ! xfer_out [15:0] $end
$var wire 1 " xfer_en $end
$var wire 8 # main_out [7:0] $end
$var wire 1 $ main_en $end
$var wire 16 % addr_out [15:0] $end
$var wire 1 & addr_en $end
$var reg 1 ' assert_addr $end
$var reg 1 ( assert_xfer $end
$var reg 1 ) asserthigh_main $end
$var reg 1 * assertlow_main $end
$var reg 16 + bus_in_addr [15:0] $end
$var reg 8 , bus_in_main [7:0] $end
$var reg 16 - bus_in_xfer [15:0] $end
$var reg 1 . clk $end
$var reg 1 / load_xfer $end
$var reg 1 0 loadhigh_main $end
$var reg 1 1 loadlow_main $end
$var reg 1 2 reset $end
$scope module register_xfer1 $end
$var wire 1 & addr_en $end
$var wire 16 3 addr_in [15:0] $end
$var wire 16 4 addr_out [15:0] $end
$var wire 1 ' assert_addr $end
$var wire 1 ( assert_xfer $end
$var wire 1 ) asserthigh_main $end
$var wire 1 * assertlow_main $end
$var wire 1 . clk $end
$var wire 1 / load_xfer $end
$var wire 1 0 loadhigh_main $end
$var wire 1 1 loadlow_main $end
$var wire 1 $ main_en $end
$var wire 8 5 main_in [7:0] $end
$var wire 1 " xfer_en $end
$var wire 16 6 xfer_in [15:0] $end
$var wire 16 7 xfer_out [15:0] $end
$var wire 8 8 main_out [7:0] $end
$var reg 16 9 value [15:0] $end
$upscope $end
$upscope $end
$enddefinitions $end
#0
$dumpvars
b0 9
b0 8
b0 7
b101010101010101 6
b0 5
b0 4
b1010101010101010 3
02
11
10
1/
0.
b101010101010101 -
b0 ,
b1010101010101010 +
1*
1)
1(
1'
0&
b0 %
0$
b0 #
0"
b0 !
$end
#5000
1.
#10000
0.
#15000
1.
1"
0(
#20000
0.
#25000
1.
0"
1(
#30000
0.
#35000
b1010101 #
b1010101 8
b101010101010101 !
b101010101010101 7
b101010101010101 %
b101010101010101 4
b101010101010101 9
1.
0/
#40000
0.
#45000
1.
1/
#50000
0.
#55000
1.
1"
0(
#60000
0.
#65000
1.
0"
1(
#70000
0.
#75000
b0 #
b0 8
b1010101 !
b1010101 7
b1010101 %
b1010101 4
b1010101 9
1.
00
#80000
0.
#85000
1.
10
#90000
0.
#95000
1.
1"
0(
#100000
0.
#105000
1.
0"
1(
#110000
0.
#115000
1.
1&
0'
#120000
0.
#125000
1.
0&
1'
#130000
0.
#135000
1.
1$
b1010101 #
b1010101 8
0*
#140000
0.
#145000
1.
0$
b0 #
b0 8
1*
#150000
0.
#155000
1.
1$
0)
#160000
0.
#165000
1.
0$
1)
