bus.v
module bus #(
    parameter WIDTH = 8,
    parameter COUNT = 8,
    parameter TOTAL_WIDTH = WIDTH * COUNT
) (
    input clk,
    input [TOTAL_WIDTH-1:0] in,
    input [COUNT-1:0] enable,
    output [WIDTH-1:0] out
);

localparam ENCODED_WIDTH = $clog2(COUNT+1);

// convert from packed data input to array of WIDTH-wide inputs
wire [WIDTH-1:0] in_array [0:COUNT];
assign in_array[0] = ~0;
generate genvar j;
    for(j = 0; j < COUNT; j = j + 1)
        assign in_array[j+1] = in[((j+1) * WIDTH)-1:(j * WIDTH)];
endgenerate

// priority encoder
wire [ENCODED_WIDTH:0] enable_encoded[0:COUNT];
assign enable_encoded[0] = 5'b00000;
generate genvar i;
    for(i = 0; i < COUNT; i = i + 1)
        assign enable_encoded[i+1] = enable[i] ? i+1 : enable_encoded[i]; 
endgenerate

wire [ENCODED_WIDTH-1:0] selected;
assign selected = enable_encoded[COUNT];
// always @(posedge clk) begin
//     $display("enable_encoded: %b -> %b", enable, enable_encoded[COUNT]);
//     $display("  0: %b", enable_encoded[0]);
//     $display("  1: %b", enable_encoded[1]);
//     $display("  2: %b", enable_encoded[2]);
//     $display("  3: %b", enable_encoded[3]);
//     $display("  4: %b", enable_encoded[4]);
// end
// always @(posedge clk) begin
//     $display("in: %h", in);
//     $display("  0: %h", in_array[0]);
//     $display("  1: %h", in_array[1]);
//     $display("  2: %h", in_array[2]);
//     $display("  3: %h", in_array[3]);
//     $display("  4: %h", in_array[4]);
// end
assign out = in_array[selected];

endmodule

register_addr/register_addr.v
module register_addr #(
    parameter WIDTH = 16, // bus width in bits
    parameter DEFAULT_VALUE = 0 // defaults to zero
) (
    input clk, inc, dec, reset,
    input [WIDTH-1:0] addr_in,
    input [WIDTH-1:0] xfer_in,
    input assert_addr, assert_xfer, load_xfer,
    output [WIDTH-1:0] addr_out,
    output [WIDTH-1:0] xfer_out,
    output addr_en, xfer_en
);
    reg [WIDTH-1:0] value = DEFAULT_VALUE;

    // do everything at a clock edge to make timing more predictable
    always @(posedge clk) begin
        // $display("  r: %b l: %b, inc: %b, dec: %b", reset, load_xfer, inc, dec);

        value <= !reset ? 0 :            // reset
                !load_xfer ? xfer_in :   // load
                !inc ? value + 1 :       // inc
                !dec ? value - 1 :       // dec
                value;                  // no change
    end

    // note that the bus takes care enable behavior, so we just output the data at all times
    assign addr_out = value;
    assign addr_en = ~assert_addr;

    assign xfer_out = value;
    assign xfer_en = ~assert_xfer;

endmodule

register_xfer/register_xfer.v
// WIDTH_AX must be 2x WIDTH_MAIN
module register_xfer #(
    parameter DEFAULT_VALUE = 0, // defaults to zero
    parameter WIDTH_AX = 16, // bus width for addr and xfer bus in bits
    parameter WIDTH_MAIN = 8 // bus width for main bus in bits
) (
    input clk,

    // address bus
    input [WIDTH_AX-1:0] addr_in,
    input assert_addr,
    output [WIDTH_AX-1:0] addr_out,
    output addr_en,

    // xfer bus
    input [WIDTH_AX-1:0] xfer_in,
    input assert_xfer, load_xfer,
    output [WIDTH_AX-1:0] xfer_out,
    output xfer_en,

    // main bus
    input [WIDTH_MAIN-1:0] main_in,
    input assertlow_main, asserthigh_main, loadlow_main, loadhigh_main,
    output [WIDTH_MAIN-1:0] main_out,
    output main_en
);
    reg [WIDTH_AX-1:0] value = DEFAULT_VALUE;

    // do everything at a clock edge to make timing more predictable
    always @(posedge clk) begin
        value <= !load_xfer ? xfer_in :   // load xfer
                !loadlow_main ? {value[WIDTH_AX-1:WIDTH_AX-WIDTH_MAIN], main_in[WIDTH_MAIN-1:0]} : // load main to low
                !loadhigh_main ? {main_in[WIDTH_MAIN-1:0], value[WIDTH_MAIN-1:0]} : // load main to high
                value;                  // no change
    end

    // note that the bus takes care enable behavior, so we just output the data at all times
    assign addr_out = value;
    assign addr_en = ~assert_addr;

    assign xfer_out = value;
    assign xfer_en = ~assert_xfer;

    // slightly weird to only use the assertlow to determine which output goes to main, but the bus handles the rest
    assign main_out = assertlow_main ? value[WIDTH_AX-1:WIDTH_AX-WIDTH_MAIN] : value[WIDTH_MAIN:0];
    // bus enable is active high, asserts are active low
    assign main_en = ~(assertlow_main & asserthigh_main);

endmodule

register_gp/register_gp.v
module register_gp #(
    parameter WIDTH = 8, // bus width in bits
    parameter DEFAULT_VALUE = 0 // defaults to "pulled up" (8'hff for 8 width, for example)
) (
    input clk,

    input [WIDTH-1:0] bus_in,
    input assert_bus,
    input load_bus,
    output [WIDTH-1:0] bus_out,
    output bus_en,

    input assert_lhs,
    output [WIDTH-1:0] lhs_out,
    output lhs_en,

    input assert_rhs,
    output [WIDTH-1:0] rhs_out,
    output rhs_en
);
    reg [WIDTH-1:0] value = DEFAULT_VALUE;

    // do everything at a clock edge to make timing more predictable
    always @(posedge clk) begin
        value <= !load_bus ? bus_in : value;
    end

    // note that the bus takes care enable behavior, so we just output the data at all times
    assign bus_out = value;
    assign bus_en = ~assert_bus;

    assign lhs_out = value;
    assign lhs_en = ~assert_lhs;

    assign rhs_out = value;
    assign rhs_en = ~assert_rhs;

endmodule

tests/tests_tb.sv
`timescale 1ns/1ps
`include "../register_gp/register_gp.v"
`include "../register_xfer/register_xfer.v"
`include "../register_addr/register_addr.v"
`include "../bus/bus.v"

module tests_tb();
    localparam WIDTH_AX = 16; // bus width for addr and xfer bus in bits
    localparam WIDTH_MAIN = 8; // bus width for main bus in bits

	reg clk = 0;
    reg reset = 0;

    // a - main bus
    // reg [WIDTH_MAIN-1:0] a_bus_in =  8'h00;
    reg a_assert_main = 1'b1;
    reg a_load_main = 1'b1;
    wire [WIDTH_MAIN-1:0] a_main_out;
    wire a_main_en;

    // a - lhs bus
    reg a_assert_lhs = 1'b1;
    wire [WIDTH_MAIN-1:0] a_lhs_out;
    wire a_lhs_en;

    // a - rhs bus
    reg a_assert_rhs = 1'b1;
    wire [WIDTH_MAIN-1:0] a_rhs_out;
    wire a_rhs_en;

    
    register_gp #(.WIDTH(WIDTH_MAIN)) a (
        .clk(clk),

        // main bus
        .bus_in(main_out),
        .load_bus(a_load_main),
        .assert_bus(a_assert_main),
        .bus_out(a_main_out), .bus_en(a_main_en),

        // lhs bus
        .assert_lhs(a_assert_lhs), .lhs_out(a_lhs_out), .lhs_en(a_lhs_en),

        // rhs bus
        .assert_rhs(a_assert_rhs), .rhs_out(a_rhs_out), .rhs_en(a_rhs_en)
    );

    // xfer - addr bus
    reg xfer_assert_addr = 1'b1;
    wire [WIDTH_AX-1:0] xfer_addr_out;
    wire xfer_addr_en;

    // xfer - xfer bus
    reg xfer_assert_xfer = 1'b1;
    reg xfer_load_xfer = 1'b1;
    wire [WIDTH_AX-1:0] xfer_xfer_out;
    wire xfer_xfer_en;

    // xfer - main bus
    // reg [WIDTH_MAIN-1:0] xfer_main_in = 8'h00;
    reg xfer_assertlow_main = 1'b1;
    reg xfer_loadlow_main = 1'b1;
    reg xfer_asserthigh_main = 1'b1;
    reg xfer_loadhigh_main = 1'b1;
    wire [WIDTH_MAIN-1:0] xfer_main_out;
    wire xfer_main_en;

    register_xfer #(.WIDTH_AX(16), .WIDTH_MAIN(8)) xfer (
        .clk(clk),

        // addr bus
        .addr_in(addr_out),
        .assert_addr(xfer_assert_addr),
        .addr_out(xfer_addr_out), .addr_en(xfer_addr_en),

        // xfer bus
        .xfer_in(xfer_out),
        .load_xfer(xfer_load_xfer),
        .assert_xfer(xfer_assert_xfer),
        .xfer_out(xfer_xfer_out), .xfer_en(xfer_xfer_en),

        // main bus
        .main_in(main_out),
        .loadlow_main(xfer_loadlow_main),
        .loadhigh_main(xfer_loadhigh_main),
        .assertlow_main(xfer_assertlow_main),
        .asserthigh_main(xfer_asserthigh_main),
        .main_out(xfer_main_out), .main_en(xfer_main_en)
    );
	

    // pcra0 - addr bus
    reg pcra0_assert_addr = 1'b1;
    wire [WIDTH_AX-1:0] pcra0_addr_out;
    wire pcra0_addr_en;

    // pcra0 - xfer bus
    reg pcra0_assert_xfer = 1'b1;
    reg pcra0_load_xfer = 1'b1;
    wire [WIDTH_AX-1:0] pcra0_xfer_out;
    wire pcra0_xfer_en;

    reg pcra0_inc = 1'b1;
    reg pcra0_dec = 1'b1;

    register_addr #(.WIDTH(WIDTH_AX)) pcra0 (
        .clk(clk),
        .reset(reset),

        .addr_in(addr_out),
        .assert_addr(pcra0_assert_addr),
        .addr_out(pcra0_addr_out),
        .addr_en(pcra0_addr_en),

        .xfer_in(xfer_out),
        .assert_xfer(pcra0_assert_xfer),
        .load_xfer(pcra0_load_xfer),
        .xfer_out(pcra0_xfer_out),
        .xfer_en(pcra0_xfer_en),

        .inc(pcra0_inc),
        .dec(pcra0_dec)
    );


    // test - main bus
    reg [WIDTH_MAIN-1:0] test_main_out = 8'h0f;
    reg test_main_en = 1'b0;
    wire [WIDTH_MAIN-1:0] main_out;

	bus #(.WIDTH(WIDTH_MAIN),.COUNT(3)) mainbus (
        .clk(clk),
        .in({
            test_main_out,
            a_main_out,
            xfer_main_out
        }),
        .enable({
            test_main_en,
            a_main_en,
            xfer_main_en
        }),
        .out(main_out)
    );

    // test - addr bus
    reg [WIDTH_AX-1:0] test_addr_out = 16'h0f;
    reg test_addr_en = 1'b0;
    wire [WIDTH_AX-1:0] addr_out;

	bus #(.WIDTH(WIDTH_AX),.COUNT(3)) addrbus (
        .clk(clk),
        .in({
            test_addr_out,
            pcra0_addr_out,
            xfer_addr_out
        }),
        .enable({
            test_addr_en,
            pcra0_addr_en,
            xfer_addr_en
        }),
        .out(addr_out)
    );

    // test - xfer bus
    reg [WIDTH_AX-1:0] test_xfer_out = 16'h0f;
    reg test_xfer_en = 1'b0;
    wire [WIDTH_AX-1:0] xfer_out;

	bus #(.WIDTH(WIDTH_AX),.COUNT(3)) xferbus (
        .clk(clk),
        .in({
            test_xfer_out,
            pcra0_xfer_out,
            xfer_xfer_out
        }),
        .enable({
            test_xfer_en,
            pcra0_xfer_en,
            xfer_xfer_en
        }),
        .out(xfer_out)
    );


	always
		#(5) clk <= !clk;

	initial
	begin
		$dumpfile("tests_tb.vcd");
		$dumpvars(0,tests_tb);

        #10 reset = 1'b1;

        #10
        test_xfer_out = 16'h5555;
        test_xfer_en = 1'b1;
        #0 assert (xfer_out == 16'h5555)
            $display   ("xfer manual test value (5555) OK");
            else $error("xfer manual test value (expected: 5555, actual: %h) NOT OK", xfer_out);
        #10 test_xfer_en = 1'b0;

        #10
        test_addr_out = 16'h5555;
        test_addr_en = 1'b1;
        #0 assert (addr_out == 16'h5555)
            $display   ("addr manual test value (5555) OK");
            else $error("addr manual test value (expected: 5555, actual: %h) NOT OK", xfer_out);
        #10 test_addr_en = 1'b0;

        #10
        test_xfer_out = 16'h5555;
        test_xfer_en = 1'b1;
        #10 pcra0_load_xfer = 1'b0;
        #10 
        test_xfer_en = 1'b0;
        pcra0_load_xfer = 1'b1;
        pcra0_assert_addr = 1'b0;
        #10 assert (addr_out == 16'h5555)
            $display   ("xfer assert to addr (5555) OK");
            else $error("xfer assert to addr (expected: 5555, actual: %h) NOT OK", addr_out);
        pcra0_assert_addr = 1'b1;


        // inc pcra0
        #10 pcra0_inc = 1'b0;
        #10 pcra0_inc = 1'b1;
        #10 pcra0_assert_addr = 1'b0;
        #10 assert (addr_out == 16'h5556)
            $display   ("pcra0 inc (5556) OK");
            else $error("pcra0 inc (expected: 5556, actual: %h) NOT OK", addr_out);
        pcra0_assert_addr = 1'b1;

        // dec pcra0
        #10 pcra0_dec = 1'b0;
        #10 pcra0_dec = 1'b1;
        #10 pcra0_assert_addr = 1'b0;
        #10 assert (addr_out == 16'h5555)
            $display   ("pcra0 dec (5555) OK");
            else $error("pcra0 dec (expected: 5555, actual: %h) NOT OK", addr_out);
        pcra0_assert_addr = 1'b1;


        // pcra0 -> xfer
        #10 pcra0_assert_xfer = 1'b0;
        #10 xfer_load_xfer = 1'b0;
        #10 xfer_load_xfer = 1'b1;
        #10 pcra0_assert_xfer = 1'b1;
        #10 xfer_assert_addr = 1'b0;
        #0 assert (addr_out == 16'h5555)
            $display   ("pcra0 to xfer (5555) OK");
            else $error("pcra0 to xfer (expected: 5555, actual: %h) NOT OK", addr_out);
        xfer_assert_addr = 1'b1;

        
        // load 55AA into XFER
        #10
        test_xfer_out = 16'h55AA;
        test_xfer_en = 1'b1;
        #10 xfer_load_xfer = 1'b0;
        #10 xfer_load_xfer = 1'b1;

        // assert XFER to main
        #10 xfer_assertlow_main = 1'b0;
        #0 assert (main_out == 8'hAA)
            $display   ("xfer assert main (AA) OK");
            else $error("xfer assert main (expected: AA, actual: %h) NOT OK", main_out);
        // latch to A
        #10 a_load_main = 1'b0;
        #10 a_load_main = 1'b1;
        // stop asserting to main
        #10 xfer_assertlow_main = 1'b1;
        #0 assert (main_out == 8'hFF)
            $display   ("xfer no longer asserting to main (FF) OK");
            else $error("xfer no longer asserting to main (expected: FF, actual: %h) NOT OK", main_out);
        #10 a_assert_main = 1'b0;
        #0 assert (main_out == 8'hAA)
            $display   ("a assert main (AA) OK");
            else $error("a assert main (expected: AA, actual: %h) NOT OK", main_out);
        xfer_assert_addr = 1'b1;
        #10 a_assert_main = 1'b1;


        // #0 $display("main bus (%b): %h", {test_main_en, a_bus_en, xfer_main_en}, main_out);

        // #10
        // test_main_out = 8'h11;
        // test_main_en = 1'b1;
        // #0 $display("main bus (%b): %h", {test_main_en, a_bus_en, xfer_main_en}, main_out);

        // #10 xfer_loadhigh_main = 1'b0;
        // #10 xfer_loadhigh_main = 1'b1;

        // #10
        // test_main_out = 8'h22;
        // test_main_en = 1'b1;
        // #0 $display("main bus (%b): %h", {test_main_en, a_bus_en, xfer_main_en}, main_out);

        // #10 xfer_loadhigh_main = 1'b0;
        // #10 xfer_loadhigh_main = 1'b1;

        // #10 xfer_assert_xfer = 1'b0;
        // #0 $display("xfer bus: %h", xfer_xfer_out);

        // #10 test_main_en = 1'b0;

        // #10 xfer_asserthigh_main = 1'b0;
        // #10 xfer_asserthigh_main = 1'b1;
        // #0 $display("main bus (%b): %h", {test_main_en, a_bus_en, xfer_main_en}, main_out);


        // #10 xfer_load_xfer = 1'b0;
        // #10 xfer_load_xfer = 1'b0;
        // #0 $display("xfer bus: %h", xfer_xfer_out);
        // #0 $display("main bus (%b): %h", {test_main_en, a_bus_en, xfer_main_en}, main_out);


        // #10 xfer_asserthigh_main = 1'b0;
        // #10 xfer_asserthigh_main = 1'b1;
        // #0 $display("main bus (%b): %h", {test_main_en, a_bus_en, xfer_main_en}, main_out);


        #10 $finish;
	end
endmodule

build/tests/tests_tb.vcd
$date
	Mon May 24 18:29:32 2021
$end
$version
	Icarus Verilog
$end
$timescale
	1ps
$end
$scope module tests_tb $end
$var wire 16 ! xfer_xfer_out [15:0] $end
$var wire 1 " xfer_xfer_en $end
$var wire 16 # xfer_out [15:0] $end
$var wire 8 $ xfer_main_out [7:0] $end
$var wire 1 % xfer_main_en $end
$var wire 16 & xfer_addr_out [15:0] $end
$var wire 1 ' xfer_addr_en $end
$var wire 16 ( pcra0_xfer_out [15:0] $end
$var wire 1 ) pcra0_xfer_en $end
$var wire 16 * pcra0_addr_out [15:0] $end
$var wire 1 + pcra0_addr_en $end
$var wire 8 , main_out [7:0] $end
$var wire 16 - addr_out [15:0] $end
$var wire 8 . a_rhs_out [7:0] $end
$var wire 1 / a_rhs_en $end
$var wire 8 0 a_main_out [7:0] $end
$var wire 1 1 a_main_en $end
$var wire 8 2 a_lhs_out [7:0] $end
$var wire 1 3 a_lhs_en $end
$var reg 1 4 a_assert_lhs $end
$var reg 1 5 a_assert_main $end
$var reg 1 6 a_assert_rhs $end
$var reg 1 7 a_load_main $end
$var reg 1 8 clk $end
$var reg 1 9 pcra0_assert_addr $end
$var reg 1 : pcra0_assert_xfer $end
$var reg 1 ; pcra0_dec $end
$var reg 1 < pcra0_inc $end
$var reg 1 = pcra0_load_xfer $end
$var reg 1 > reset $end
$var reg 1 ? test_addr_en $end
$var reg 16 @ test_addr_out [15:0] $end
$var reg 1 A test_main_en $end
$var reg 8 B test_main_out [7:0] $end
$var reg 1 C test_xfer_en $end
$var reg 16 D test_xfer_out [15:0] $end
$var reg 1 E xfer_assert_addr $end
$var reg 1 F xfer_assert_xfer $end
$var reg 1 G xfer_asserthigh_main $end
$var reg 1 H xfer_assertlow_main $end
$var reg 1 I xfer_load_xfer $end
$var reg 1 J xfer_loadhigh_main $end
$var reg 1 K xfer_loadlow_main $end
$scope module a $end
$var wire 1 5 assert_bus $end
$var wire 1 4 assert_lhs $end
$var wire 1 6 assert_rhs $end
$var wire 1 1 bus_en $end
$var wire 8 L bus_out [7:0] $end
$var wire 1 8 clk $end
$var wire 1 3 lhs_en $end
$var wire 8 M lhs_out [7:0] $end
$var wire 1 7 load_bus $end
$var wire 1 / rhs_en $end
$var wire 8 N rhs_out [7:0] $end
$var wire 8 O bus_in [7:0] $end
$var reg 8 P value [7:0] $end
$upscope $end
$scope module addrbus $end
$var wire 1 8 clk $end
$var wire 3 Q enable [2:0] $end
$var wire 48 R in [47:0] $end
$var wire 16 S out [15:0] $end
$var wire 2 T selected [1:0] $end
$scope begin genblk1[0] $end
$upscope $end
$scope begin genblk1[1] $end
$upscope $end
$scope begin genblk1[2] $end
$upscope $end
$scope begin genblk2[0] $end
$upscope $end
$scope begin genblk2[1] $end
$upscope $end
$scope begin genblk2[2] $end
$upscope $end
$upscope $end
$scope module mainbus $end
$var wire 1 8 clk $end
$var wire 3 U enable [2:0] $end
$var wire 24 V in [23:0] $end
$var wire 8 W out [7:0] $end
$var wire 2 X selected [1:0] $end
$scope begin genblk1[0] $end
$upscope $end
$scope begin genblk1[1] $end
$upscope $end
$scope begin genblk1[2] $end
$upscope $end
$scope begin genblk2[0] $end
$upscope $end
$scope begin genblk2[1] $end
$upscope $end
$scope begin genblk2[2] $end
$upscope $end
$upscope $end
$scope module pcra0 $end
$var wire 1 + addr_en $end
$var wire 16 Y addr_in [15:0] $end
$var wire 16 Z addr_out [15:0] $end
$var wire 1 9 assert_addr $end
$var wire 1 : assert_xfer $end
$var wire 1 8 clk $end
$var wire 1 ; dec $end
$var wire 1 < inc $end
$var wire 1 = load_xfer $end
$var wire 1 > reset $end
$var wire 1 ) xfer_en $end
$var wire 16 [ xfer_out [15:0] $end
$var wire 16 \ xfer_in [15:0] $end
$var reg 16 ] value [15:0] $end
$upscope $end
$scope module xfer $end
$var wire 1 ' addr_en $end
$var wire 16 ^ addr_in [15:0] $end
$var wire 16 _ addr_out [15:0] $end
$var wire 1 E assert_addr $end
$var wire 1 F assert_xfer $end
$var wire 1 G asserthigh_main $end
$var wire 1 H assertlow_main $end
$var wire 1 8 clk $end
$var wire 1 I load_xfer $end
$var wire 1 J loadhigh_main $end
$var wire 1 K loadlow_main $end
$var wire 1 % main_en $end
$var wire 8 ` main_in [7:0] $end
$var wire 1 " xfer_en $end
$var wire 16 a xfer_out [15:0] $end
$var wire 16 b xfer_in [15:0] $end
$var wire 8 c main_out [7:0] $end
$var reg 16 d value [15:0] $end
$upscope $end
$scope module xferbus $end
$var wire 1 8 clk $end
$var wire 3 e enable [2:0] $end
$var wire 48 f in [47:0] $end
$var wire 16 g out [15:0] $end
$var wire 2 h selected [1:0] $end
$scope begin genblk1[0] $end
$upscope $end
$scope begin genblk1[1] $end
$upscope $end
$scope begin genblk1[2] $end
$upscope $end
$scope begin genblk2[0] $end
$upscope $end
$scope begin genblk2[1] $end
$upscope $end
$scope begin genblk2[2] $end
$upscope $end
$upscope $end
$upscope $end
$enddefinitions $end
#0
$dumpvars
b0 h
b1111111111111111 g
b111100000000000000000000000000000000 f
b0 e
b0 d
b0 c
b1111111111111111 b
b0 a
b11111111 `
b0 _
b1111111111111111 ^
b0 ]
b1111111111111111 \
b0 [
b0 Z
b1111111111111111 Y
b0 X
b11111111 W
b11110000000000000000 V
b0 U
b0 T
b1111111111111111 S
b111100000000000000000000000000000000 R
b0 Q
b0 P
b11111111 O
b0 N
b0 M
b0 L
1K
1J
1I
1H
1G
1F
1E
b1111 D
0C
b1111 B
0A
b1111 @
0?
0>
1=
1<
1;
1:
19
08
17
16
15
14
03
b0 2
01
b0 0
0/
b0 .
b1111111111111111 -
b11111111 ,
0+
b0 *
0)
b0 (
0'
b0 &
0%
b0 $
b1111111111111111 #
0"
b0 !
$end
#5000
18
#10000
08
1>
#15000
18
#20000
08
b101010101010101 #
b101010101010101 \
b101010101010101 b
b101010101010101 g
b11 h
b100 e
1C
b10101010101010100000000000000000000000000000000 f
b101010101010101 D
#25000
18
#30000
08
b1111111111111111 #
b1111111111111111 \
b1111111111111111 b
b1111111111111111 g
b0 h
b0 e
0C
#35000
18
#40000
08
b101010101010101 -
b101010101010101 S
b101010101010101 Y
b101010101010101 ^
b11 T
b100 Q
1?
b10101010101010100000000000000000000000000000000 R
b101010101010101 @
#45000
18
#50000
08
b1111111111111111 -
b1111111111111111 S
b1111111111111111 Y
b1111111111111111 ^
b0 T
b0 Q
0?
#55000
18
#60000
08
b101010101010101 #
b101010101010101 \
b101010101010101 b
b101010101010101 g
b11 h
b100 e
1C
#65000
18
#70000
08
0=
#75000
b10101010101010101010101010101010000000000000000 f
b101010101010101 (
b101010101010101 [
b10101010101010101010101010101010000000000000000 R
b101010101010101 *
b101010101010101 Z
b101010101010101 ]
18
#80000
08
b101010101010101 -
b101010101010101 S
b101010101010101 Y
b101010101010101 ^
b10 T
b1111111111111111 #
b1111111111111111 \
b1111111111111111 b
b1111111111111111 g
b0 h
b10 Q
1+
09
1=
b0 e
0C
#85000
18
#90000
08
b1111111111111111 -
b1111111111111111 S
b1111111111111111 Y
b1111111111111111 ^
b0 T
b0 Q
0+
19
#95000
18
#100000
08
0<
#105000
b10101010101010101010101010101100000000000000000 f
b101010101010110 (
b101010101010110 [
b10101010101010101010101010101100000000000000000 R
b101010101010110 *
b101010101010110 Z
b101010101010110 ]
18
#110000
08
1<
#115000
18
#120000
08
b101010101010110 -
b101010101010110 S
b101010101010110 Y
b101010101010110 ^
b10 T
b10 Q
1+
09
#125000
18
#130000
08
b1111111111111111 -
b1111111111111111 S
b1111111111111111 Y
b1111111111111111 ^
b0 T
b0 Q
0+
19
#135000
18
#140000
08
0;
#145000
b10101010101010101010101010101010000000000000000 f
b101010101010101 (
b101010101010101 [
b10101010101010101010101010101010000000000000000 R
b101010101010101 *
b101010101010101 Z
b101010101010101 ]
18
#150000
08
1;
#155000
18
#160000
08
b101010101010101 -
b101010101010101 S
b101010101010101 Y
b101010101010101 ^
b10 T
b10 Q
1+
09
#165000
18
#170000
08
b1111111111111111 -
b1111111111111111 S
b1111111111111111 Y
b1111111111111111 ^
b0 T
b0 Q
0+
19
#175000
18
#180000
08
b101010101010101 #
b101010101010101 \
b101010101010101 b
b101010101010101 g
b10 h
b10 e
1)
0:
#185000
18
#190000
08
0I
#195000
b11110000000001010101 V
b1010101 $
b1010101 c
b10101010101010101010101010101010101010101010101 f
b101010101010101 !
b101010101010101 a
b10101010101010101010101010101010101010101010101 R
b101010101010101 &
b101010101010101 _
b101010101010101 d
18
#200000
08
1I
#205000
18
#210000
08
b1111111111111111 #
b1111111111111111 \
b1111111111111111 b
b1111111111111111 g
b0 h
b0 e
0)
1:
#215000
18
#220000
08
b1111111111111111 -
b1111111111111111 S
b1111111111111111 Y
b1111111111111111 ^
b0 T
b0 Q
0'
1E
#225000
18
#230000
08
b101010110101010 #
b101010110101010 \
b101010110101010 b
b101010110101010 g
b11 h
b100 e
1C
b10101011010101001010101010101010101010101010101 f
b101010110101010 D
#235000
18
#240000
08
0I
#245000
b10101011010101001010101010101010101010110101010 f
b101010110101010 !
b101010110101010 a
b10101010101010101010101010101010101010110101010 R
b101010110101010 &
b101010110101010 _
b101010110101010 d
18
#250000
08
1I
#255000
18
#260000
08
b10101010 ,
b10101010 O
b10101010 W
b10101010 `
b1 X
b1 U
1%
b11110000000010101010 V
b10101010 $
b10101010 c
0H
#265000
18
#270000
08
07
#275000
b10101010 .
b10101010 N
b10101010 2
b10101010 M
b11111010101010101010 V
b10101010 0
b10101010 L
b10101010 P
18
#280000
08
17
#285000
18
#290000
08
b0 X
b11111111 ,
b11111111 O
b11111111 W
b11111111 `
b0 U
0%
b11111010101001010101 V
b1010101 $
b1010101 c
1H
#295000
18
#300000
08
b10101010 ,
b10101010 O
b10101010 W
b10101010 `
b10 X
b10 U
11
05
#305000
18
#310000
08
b11111111 ,
b11111111 O
b11111111 W
b11111111 `
b0 X
b0 U
01
15
