register_gp/register_gp.v
module register_gp #(
    parameter WIDTH = 8, // bus width in bits
    parameter DEFAULT_VALUE = 0 // defaults to "pulled up" (8'hff for 8 width, for example)
) (
    input clk,

    input [WIDTH-1:0] bus_in,
    input assert_bus,
    input load_bus,
    output [WIDTH-1:0] bus_out,
    output bus_en,

    input assert_lhs,
    output [WIDTH-1:0] lhs_out,
    output lhs_en,

    input assert_rhs,
    output [WIDTH-1:0] rhs_out,
    output rhs_en
);
    reg [WIDTH-1:0] value = DEFAULT_VALUE;

    // do everything at a clock edge to make timing more predictable
    always @(posedge clk) begin
        value <= !load_bus ? bus_in : value;
    end

    // note that the bus takes care enable behavior, so we just output the data at all times
    assign bus_out = value;
    assign bus_en = ~assert_bus;

    assign lhs_out = value;
    assign lhs_en = ~assert_lhs;

    assign rhs_out = value;
    assign rhs_en = ~assert_rhs;

endmodule

register_gp/register_gp_tb.v
`timescale 1ns/1ps 
module bus_tb();
	reg clk = 0;
    reg [7:0] bus_in_a = 8'h01;
    // reg [7:0] bus_in_b = 8'h02;
    // reg [7:0] bus_in_c = 8'h03;
    // reg [7:0] bus_in_d = 8'h04;
    reg assert_bus = 1'b0;
    reg assert_lhs = 1'b0;
    reg assert_rhs = 1'b0;

    reg load_bus = 1'b0;

    register_gp #(.WIDTH(8)) register_gp1 (
        .clk(clk),
        .bus_in(bus_in_a),
        .assert_lhs(assert_lhs),
        .assert_rhs(assert_rhs),
        .assert_bus(assert_bus),
        .load_bus(load_bus)
    );
	
    // bus #(.WIDTH(8),.COUNT(4)) top1 (.clk(clk), .in({bus_in_a,bus_in_b,bus_in_c,bus_in_d}),.enable(en_in));

	always
		#(5) clk <= !clk;

	initial
	begin
		$display("test");
		$dumpfile("register_gp_tb.vcd");
		$dumpvars(0,bus_tb);
        #5
		assert_bus = 1'b1;
        #10
		assert_rhs = 1'b1;
        #10
		assert_lhs = 1'b1;
        #10
        assert_bus = 1'b0;
        #10
		load_bus = 1'b1;
        #10
        load_bus = 1'b0;
        #10
        assert_bus = 1'b1;
        #10
		$finish;
	end
endmodule

build/register_gp/register_gp_tb.vcd
$date
	Wed May  5 09:42:22 2021
$end
$version
	Icarus Verilog
$end
$timescale
	1ps
$end
$scope module bus_tb $end
$var reg 1 ! assert_bus $end
$var reg 1 " assert_lhs $end
$var reg 1 # assert_rhs $end
$var reg 8 $ bus_in_a [7:0] $end
$var reg 1 % clk $end
$var reg 1 & load_bus $end
$scope module register_gp1 $end
$var wire 1 ! assert_bus $end
$var wire 1 " assert_lhs $end
$var wire 1 # assert_rhs $end
$var wire 1 ' bus_en $end
$var wire 8 ( bus_in [7:0] $end
$var wire 8 ) bus_out [7:0] $end
$var wire 1 % clk $end
$var wire 1 * lhs_en $end
$var wire 8 + lhs_out [7:0] $end
$var wire 1 & load_bus $end
$var wire 1 , rhs_en $end
$var wire 8 - rhs_out [7:0] $end
$var reg 8 . value [7:0] $end
$upscope $end
$upscope $end
$enddefinitions $end
#0
$dumpvars
b0 .
b0 -
0,
b0 +
0*
b0 )
b1 (
0'
0&
0%
b1 $
0#
0"
0!
$end
#5000
1%
1'
1!
#10000
0%
#15000
1%
1,
1#
#20000
0%
#25000
1%
1*
1"
#30000
0%
#35000
1%
0'
0!
#40000
0%
#45000
b1 -
b1 +
b1 )
b1 .
1%
1&
#50000
0%
#55000
1%
0&
#60000
0%
#65000
1%
1'
1!
