mem/mem.v
module mem #(
    parameter WIDTH_ADDR = 16,
    parameter WIDTH = 8,
    parameter MEM_SIZE = 65535,
    parameter DEFAULT_VALUE = 0
) (
    input clk,
    
    // addr bus
    input [WIDTH_ADDR-1:0] addr_in,

    input bus_dir, // low = main -> mem ; high = mem -> main

    input [WIDTH-1:0] main_in,
    input assert_main, load_main,
    output [WIDTH-1:0] main_out,
    output main_en,

    // mem bus
    // input [WIDTH-1:0] bus_in,
    output [WIDTH-1:0] bus_out
);
    reg [WIDTH-1:0] memory [0:MEM_SIZE];

    integer i;
    initial begin
        for (i = 0; i <= MEM_SIZE; i++) begin
            memory[i] = DEFAULT_VALUE;
        end
    end
    // reg [WIDTH-1:0] data;

    always @(posedge clk) begin
        if(load_main & !bus_dir)
            memory[addr_in] <= main_in;
    end

    assign bus_out = !bus_dir ? main_in : memory[addr_in];

    assign main_out = memory[addr_in];
    assign main_en = bus_dir & !assert_main;

endmodule

mem/mem_tb.sv
`timescale 1ns/1ps 
`include "mem.v"
module mem_tb();
	localparam WIDTH_ADDR = 16;
    localparam WIDTH = 8;

	reg clk = 0;

	reg [WIDTH_ADDR-1:0] addr_in = 16'h0000;
	reg mem_busdir = 1;
	reg [WIDTH-1:0] main_in = ~0;
	reg mem_assert_main = 1;
	reg mem_load_main = 1;

	wire [WIDTH-1:0] main_out;
	wire main_en;

	wire [WIDTH-1:0] mem_out;

	mem #(.WIDTH(WIDTH)) mem1 (
		.clk(clk),

		.addr_in(addr_in),

		.bus_dir(mem_busdir), // low = main->mem ; high = mem->main

		// main bus
		.main_in(main_in),
		.assert_main(mem_assert_main),
		.load_main(mem_load_main),
		.main_out(main_out),
		.main_en(main_en),

		// mem bus
		// .bus_in(mem_in),
		.bus_out(mem_out)
	);
	
	always
		#(1) clk <= !clk;
	initial
	begin
		$dumpfile("mem_tb.vcd");
		$dumpvars(0,mem_tb);

		#1


		#2 // 8000 = AA
		mem_busdir = 0; // main->mem
		addr_in = 16'h8000;
		main_in = 8'hAA;
		#1 mem_load_main = 0;
		#1 mem_load_main = 1;

		#2 // output current mem value to main bus
		// main_en should be high (asserting to main)
		// both bus_out and main_out should be AA
		mem_busdir = 1;
		mem_assert_main = 0;
		#2

		#2 // 8001 = 55
		mem_busdir = 0; // main->mem
		addr_in = 16'h8001;
		main_in = 8'h55;
		#1 mem_load_main = 0;
		#1 mem_load_main = 1;

		#2 // output current mem value to main bus
		// main_en should be high (asserting to main)
		// both bus_out and main_out should be 55
		mem_busdir = 1;
		mem_assert_main = 0;
		#2

		#2 // read 8000 again
		// main_en should still be high (asserting to main)
		// both bus_out and main_out should be 55
		addr_in = 16'h8000;
		#2

		#2 // make sure mem bus outputs the value even if we're not asserting to main bus
		// main_en should be low, main_out is irrelevant, bus_out should still be AA
		mem_assert_main = 1;
		#2


        #10 $finish;
	end
endmodule

build/mem/mem_tb.vcd
$date
	Tue May 18 18:35:57 2021
$end
$version
	Icarus Verilog
$end
$timescale
	1ps
$end
$scope module mem_tb $end
$var wire 8 ! mem_out [7:0] $end
$var wire 8 " main_out [7:0] $end
$var wire 1 # main_en $end
$var reg 16 $ addr_in [15:0] $end
$var reg 1 % clk $end
$var reg 8 & main_in [7:0] $end
$var reg 1 ' mem_assert_main $end
$var reg 1 ( mem_busdir $end
$var reg 1 ) mem_load_main $end
$scope module mem1 $end
$var wire 16 * addr_in [15:0] $end
$var wire 1 ' assert_main $end
$var wire 1 ( bus_dir $end
$var wire 1 % clk $end
$var wire 1 ) load_main $end
$var wire 1 # main_en $end
$var wire 8 + main_in [7:0] $end
$var wire 8 , main_out [7:0] $end
$var wire 8 - bus_out [7:0] $end
$var integer 32 . i [31:0] $end
$upscope $end
$upscope $end
$enddefinitions $end
#0
$dumpvars
b10000000000000000 .
b0 -
b0 ,
b11111111 +
b0 *
1)
1(
1'
b11111111 &
0%
b0 $
0#
b0 "
b0 !
$end
#1000
1%
#2000
0%
b10101010 !
b10101010 -
0)
b10101010 &
b10101010 +
b1000000000000000 $
b1000000000000000 *
0(
#3000
b10101010 "
b10101010 ,
1%
1)
#4000
0%
#5000
1%
1#
0'
1(
#6000
0%
#7000
1%
#8000
0%
#9000
1%
0#
b1010101 !
b1010101 -
b1010101 &
b1010101 +
b1010101 "
b1010101 ,
b1000000000000001 $
b1000000000000001 *
0(
#10000
0%
0)
#11000
1%
1)
#12000
0%
#13000
1%
1#
1(
#14000
0%
#15000
1%
#16000
0%
#17000
1%
b10101010 !
b10101010 -
b10101010 "
b10101010 ,
b1000000000000000 $
b1000000000000000 *
#18000
0%
#19000
1%
#20000
0%
#21000
1%
0#
1'
