register_addr/register_addr.v
module register_addr #(
    parameter WIDTH = 16, // bus width in bits
    parameter DEFAULT_VALUE = 0 // defaults to zero
) (
    input clk, inc, dec, reset,
    input [WIDTH-1:0] addr_in,
    input [WIDTH-1:0] xfer_in,
    input assert_addr, assert_xfer, load_xfer,
    output [WIDTH-1:0] addr_out,
    output [WIDTH-1:0] xfer_out,
    output addr_en, xfer_en
);
    reg [WIDTH-1:0] value = DEFAULT_VALUE;

    // do everything at a clock edge to make timing more predictable
    always @(posedge clk) begin
        // $display("  r: %b l: %b, inc: %b, dec: %b", reset, load_xfer, inc, dec);

        value <= !reset ? 0 :            // reset
                !load_xfer ? xfer_in :   // load
                !inc ? value + 1 :       // inc
                !dec ? value - 1 :       // dec
                value;                  // no change
    end

    // note that the bus takes care enable behavior, so we just output the data at all times
    assign addr_out = value;
    assign addr_en = ~assert_addr;

    assign xfer_out = value;
    assign xfer_en = ~assert_xfer;

endmodule

register_addr_tb.v
`timescale 1ns/1ps 
module bus_tb();
	reg clk = 0;
    reg reset = 0;
    reg [15:0] bus_in_a = 16'h01;
    reg [15:0] bus_in_b = 16'h02;
    // reg [7:0] bus_in_c = 8'h03;
    // reg [7:0] bus_in_d = 8'h04;
    reg assert_addr = 1'b0;
    reg assert_xfer = 1'b0;

    reg load_xfer = 1'b0;
    reg inc = 1'b0;
    reg dec = 1'b0;



    register_addr #(.WIDTH(16)) register_addr1 (
        .clk(clk),
        .reset(reset),
        .addr_in(bus_in_a),
        .xfer_in(bus_in_b),
        .assert_addr(assert_lhs),
        .assert_xfer(assert_rhs),
        .load_xfer(load_xfer),
        .inc(inc),
        .dec(dec)
    );
	
    // bus #(.WIDTH(8),.COUNT(4)) top1 (.clk(clk), .in({bus_in_a,bus_in_b,bus_in_c,bus_in_d}),.enable(en_in));

	always
		#(5) clk <= !clk;

	initial
	begin
		$display("test");
		$dumpfile("register_addr_tb.vcd");
		$dumpvars(0,bus_tb);
        #5
		assert_addr = 1'b1;
		#10
		assert_xfer = 1'b1;
		#10
		load_xfer = 1'b1;
        #10
        load_xfer = 1'b0;
        #10
        assert_addr = 1'b1;
        #10
        inc = 1'b1;
        #10
        inc = 1'b0;
        #10
        dec = 1'b1;
        #10
        dec = 1'b0;
        #10
        reset = 1'b1;
        #10
        reset = 1'b0;
        #10
		$finish;
	end
endmodule

build/register_addr/register_addr_tb.vcd
$date
	Wed May  5 09:40:53 2021
$end
$version
	Icarus Verilog
$end
$timescale
	1ps
$end
$scope module bus_tb $end
$var wire 1 ! assert_lhs $end
$var wire 1 " assert_rhs $end
$var reg 1 # assert_addr $end
$var reg 1 $ assert_xfer $end
$var reg 16 % bus_in_a [15:0] $end
$var reg 16 & bus_in_b [15:0] $end
$var reg 1 ' clk $end
$var reg 1 ( dec $end
$var reg 1 ) inc $end
$var reg 1 * load_xfer $end
$var reg 1 + reset $end
$scope module register_addr1 $end
$var wire 1 , addr_en $end
$var wire 16 - addr_in [15:0] $end
$var wire 16 . addr_out [15:0] $end
$var wire 1 ! assert_addr $end
$var wire 1 " assert_xfer $end
$var wire 1 ' clk $end
$var wire 1 ( dec $end
$var wire 1 ) inc $end
$var wire 1 * load_xfer $end
$var wire 1 + reset $end
$var wire 1 / xfer_en $end
$var wire 16 0 xfer_in [15:0] $end
$var wire 16 1 xfer_out [15:0] $end
$var reg 16 2 value [15:0] $end
$upscope $end
$upscope $end
$enddefinitions $end
#0
$dumpvars
b0 2
b0 1
b10 0
z/
b0 .
b1 -
z,
0+
0*
0)
0(
0'
b10 &
b1 %
0$
0#
z"
z!
$end
#5000
1'
1#
#10000
0'
#15000
1'
1$
#20000
0'
#25000
b10 1
b10 .
b10 2
1'
1*
#30000
0'
#35000
1'
0*
#40000
0'
#45000
1'
#50000
0'
#55000
b11 1
b11 .
b11 2
1'
1)
#60000
0'
#65000
1'
0)
#70000
0'
#75000
b10 1
b10 .
b10 2
1'
1(
#80000
0'
#85000
1'
0(
#90000
0'
#95000
b0 1
b0 .
b0 2
1'
1+
#100000
0'
#105000
1'
0+
