alu/rhs/rhs.v
module rhs #(
    parameter WIDTH = 8
) (
    input clk,
    input alu_clk,
    input [3:0] operation,
    input [WIDTH-1:0] lhs_in,
    input [WIDTH-1:0] rhs_in,
    output reg [WIDTH-1:0] out
);
    initial begin
        out = 0;
    end
    // do everything at a clock edge to make timing more predictable
    always @(posedge alu_clk) begin
        case (operation)
            4'b0000: out <= 0;                      // zero
            4'b0001: out <= ~(lhs_in | rhs_in);     // nor
            4'b0010: out <= lhs_in & ~rhs_in;       // A !B
            4'b0011: out <= ~rhs_in;                // !B Pass
            4'b0100: out <= ~lhs_in & rhs_in;       // !A B
            4'b0101: out <= ~lhs_in;                // !A Pass
            4'b0110: out <= lhs_in ^ rhs_in;        // A ^ B (XOR)
            4'b0111: out <= ~(lhs_in & rhs_in);     // NAND
            4'b1000: out <= lhs_in & rhs_in;        // AND
            4'b1001: out <= ~(lhs_in ^ rhs_in);     // XNOR
            4'b1010: out <= lhs_in;                 // A Pass
            4'b1011: out <= lhs_in | ~rhs_in;       // A+!B
            4'b1100: out <= rhs_in;                 // B Pass
            4'b1101: out <= ~lhs_in | rhs_in;       // !A + B
            4'b1110: out <= lhs_in | rhs_in;        // OR
            4'b1111: out <= ~0;                     // ~zero 
        endcase
    end
endmodule

alu/lhs/lhs.v
module lhs #(
    parameter WIDTH = 8
) (
    input clk,
    input alu_clk,
    input [1:0] operation,
    input [WIDTH-1:0] in,
    input carry_in,
    output reg [WIDTH-1:0] out,
    output reg carry_out
);
    initial begin
        out = 0;
        carry_out = 0;
    end

    // missing ALU clock functionality (separate from regular clock)

    // do everything at a clock edge to make timing more predictable
    always @(posedge alu_clk) begin
        // if (alu_clk) begin
            case (operation)
                // Zero
                2'b11: begin
                    carry_out <= 0;
                    out <= 0;
                end
                // Shift Right
                2'b10: begin
                    carry_out <= in[0];
                    out <= {carry_in, in[WIDTH-1:1]};
                end
                // Shift Left
                2'b01: begin
                    carry_out <= in[WIDTH-1];
                    out <= {in[WIDTH-2:0], carry_in};
                end
                // Pass Through
                default: begin
                    carry_out <= carry_in;
                    out <= in;
                end
            endcase
        // end else begin
        //     carry_out <= carry_out;
        //     out <= out;
        // end
    end
endmodule

alu/alu_op.v
module alu_op (
    input clk,

    input [3:0] operation,
    output alu_clk,
    output [3:0] logic_op,
    output [1:0] shift_select,
    output [1:0] carry_select
);
    reg [7:0] ops [0:15];
    initial begin
                                // operation        carry   lhs     rhs
        ops[0]  = 8'b00000000;  // no op            0       lhs     0
        ops[1]  = 8'b00010000;  // shift left       0       <<lhs   0
        ops[2]  = 8'b00100000;  // shift right      0       >>lhs   0
        ops[3]  = 8'b00001100;  // add              0       lhs     rhs
        ops[4]  = 8'b01001100;  // addc             prev    lhs     rhs
        ops[5]  = 8'b10000000;  // inc              1       lhs     0
        ops[6]  = 8'b01000000;  // incc             prev    lhs     0       
        ops[7]  = 8'b10000011;  // sub              1       lhs     ~rhs
        ops[8]  = 8'b01000011;  // subb             prev    lhs     ~rhs
        ops[9]  = 8'b00001111;  // dec              0       lhs     ~0
        ops[10] = 8'b00111000;  // and              0       0       lhs AND rhs
        ops[11] = 8'b00111110;  // or               0       0       lhs OR  rhs
        ops[12] = 8'b00110110;  // xor              0       0       lhs XOR rhs
        ops[13] = 8'b00110011;  // not              0       0       ~rhs
        ops[14] = 8'b00110000;  // clc              0       0       0
        ops[15] = 8'b00110000;  // unused           0       0       0
    end
    wire [7:0] current_op = ops[operation];
    assign logic_op = current_op[3:0];
    assign shift_select = current_op[5:4];
    assign carry_select = current_op[7:6];

    // generate alu clk
    wire select0 = ~|operation;         // select 0 is high when all operation bits are low (NOR reduction)
    // assign alu_clk = ~(~clk | select0); // alu_clk should mirror clk when select0 is low
    assign alu_clk = ~select0  & clk;

    // always @(posedge clk) begin
    //     case (operation) 
    //         4'b0000: begin              // no op
    //             carry_select <= 2'b00;      //
    //             shift_select <= 2'b00;      // lhs
    //             logic_op <= 4'b0000;        //
    //         end
    //         4'b0001: begin              // shift left
    //             carry_select <= 2'b00;      // 
    //             shift_select <= 2'b01;      // shl lhs
    //             logic_op <= 4'b0000;        // 0
    //         end
    //         4'b0010: begin              // shift right
    //             carry_select <= 2'b00;      //
    //             shift_select <= 2'b10;      // shr lhs
    //             logic_op <= 4'b0000;        // 0
    //         end
    //         4'b0011: begin              // add
    //             carry_select <= 2'b00;      // 
    //             shift_select <= 2'b00;      // lhs
    //             logic_op <= 4'b1100;        // rhs
    //         end
    //         4'b0100: begin              // addc
    //             carry_select <= 2'b01;      // prev carry?
    //             shift_select <= 2'b00;      // lhs
    //             logic_op <= 4'b1100;        // rhs
    //         end
    //         4'b0101: begin              // inc
    //             carry_select <= 2'b10;      // 1?
    //             shift_select <= 2'b00;      // lhs
    //             logic_op <= 4'b0000;        // 0
    //         end
    //         4'b0110: begin              // incc
    //             carry_select <= 2'b01;      // prev carry?
    //             shift_select <= 2'b00;      // lhs
    //             logic_op <= 4'b0000;        // 0
    //         end
    //         4'b0111: begin              // sub
    //             carry_select <= 2'b10;      // 1?
    //             shift_select <= 2'b00;      // lhs
    //             logic_op <= 4'b0011;        // ~rhs
    //         end
    //         4'b1000: begin              // subb
    //             carry_select <= 2'b01;      // prev carry?
    //             shift_select <= 2'b00;      // lhs
    //             logic_op <= 4'b0011;        // ~rhs
    //         end
    //         4'b1001: begin              // dec
    //             carry_select <= 2'b00;      // 0?
    //             shift_select <= 2'b00;      // lhs
    //             logic_op <= 4'b1111;        // ~0 (-1)
    //         end
    //         4'b1010: begin              // and
    //             carry_select <= 2'b00;      // 0?
    //             shift_select <= 2'b11;      // 0
    //             logic_op <= 4'b1000;        // AND
    //         end
    //         4'b1011: begin              // or
    //             carry_select <= 2'b00;      // 0
    //             shift_select <= 2'b11;      // 0
    //             logic_op <= 4'b1110;        // OR
    //         end
    //         4'b1100: begin              // xor
    //             carry_select <= 2'b00;      // 0
    //             shift_select <= 2'b11;      // 0
    //             logic_op <= 4'b0110;        // XOR
    //         end
    //         4'b1101: begin              // not
    //             carry_select <= 2'b00;      // 0
    //             shift_select <= 2'b11;      // 0
    //             logic_op <= 4'b0011;        // ~rhs
    //         end
    //         4'b1110: begin              // clc
    //             shift_select <= 2'b00;      // 0
    //             carry_select <= 2'b11;      // 0      
    //             logic_op <= 4'b0000;        // 0
    //         end
    //         4'b1111: begin              // unused?
    //             logic_op <= 4'b0000;
    //             shift_select <= 2'b00;
    //             carry_select <= 2'b00;
    //         end
    //     endcase        
    // end

endmodule

alu/alu.v
`include "alu_op.v"
`include "lhs/lhs.v"
`include "rhs/rhs.v"
module alu #(
    parameter WIDTH = 8
) (
    input clk,

    input [WIDTH-1:0] lhs_in,
    input [WIDTH-1:0] rhs_in,
    input [3:0] operation,
    input assert_bus,
    output [WIDTH-1:0] bus_out,
    output bus_en,

    output reg flag_zero, flag_acarry, flag_lcarry, flag_sign, flag_overflow
);

    wire alu_clk;
    wire [3:0] aluop_logic_op;
    wire [1:0] aluop_shift_select;
    wire [1:0] aluop_carry_select;

    alu_op alu_op1 (
        .clk(clk),
        .alu_clk(alu_clk),
        .operation(operation),
        .logic_op(aluop_logic_op),
        .shift_select(aluop_shift_select),
        .carry_select(aluop_carry_select)
	);

    reg lhs_carry_in = 0;
    wire [WIDTH-1:0] lhs_out;
    wire lhs_carry_out;

    lhs #(.WIDTH(WIDTH)) lhs1 (
        .clk(clk),
        .alu_clk(alu_clk),
        .operation(aluop_shift_select),
        .in(lhs_in),
        .carry_in(lhs_carry_in),
        .out(lhs_out),
        .carry_out(lhs_carry_out)
    );
	
    wire [WIDTH-1:0] rhs_out;
    rhs #(.WIDTH(WIDTH)) rhs1 (
        .clk(clk),
        .alu_clk(alu_clk),
        .operation(aluop_logic_op),
        .lhs_in(lhs_in),
        .rhs_in(rhs_in),
        .out(rhs_out)
    );

    wire carry = aluop_carry_select[1]
        ? (aluop_carry_select[0] ? 0 : 1)
        : (aluop_carry_select[0] ? prev_carry : 0);

    reg prev_carry = 1'b0;

    wire [WIDTH:0] result = lhs_out + rhs_out + carry;

    assign bus_out = result[WIDTH-1:0];
    assign bus_en = ~assert_bus;

    // do everything at a clock edge to make timing more predictable
    always @(posedge alu_clk) begin
        prev_carry = result[WIDTH];
    end

endmodule

alu/alu_tb.sv
`timescale 1ns/1ps 
`include "alu.v"
module alu_tb();
    localparam WIDTH = 8;

	reg clk = 0;
	reg [3:0] operation = 0;
	reg [WIDTH-1:0] lhs_in = 0;
	reg [WIDTH-1:0] rhs_in = 0;

	reg assert_bus;
	wire [WIDTH-1:0] bus_out;
	wire bus_en;
	wire flag_zero, flag_acarry, flag_lcarry, flag_sign, flag_overflow;

	alu #(.WIDTH(WIDTH)) alu1 (
		.clk(clk),

		.lhs_in(lhs_in),
		.rhs_in(rhs_in),
		.operation(operation),
		.assert_bus(assert_bus),
		.bus_out(bus_out),
		.bus_en(bus_en),
		.flag_zero(flag_zero),
		.flag_acarry(flag_acarry),
		.flag_lcarry(flag_lcarry),
		.flag_sign(flag_sign),
		.flag_overflow(flag_overflow)
	);
  
	// reg [3:0] aluop_operation = 4'b0000;
    // wire [3:0] aluop_logic_op;
    // wire [1:0] aluop_shift_select;
    // wire [1:0] aluop_carry_select;
    // alu_op alu_op1 (
    //     .clk(clk),
    //     .operation(aluop_operation),
    //     .logic_op(aluop_logic_op),
    //     .shift_select(aluop_shift_select),
    //     .carry_select(aluop_carry_select)
	// );
	always
		#(1) clk <= !clk;
	initial
	begin
		$dumpfile("alu_tb.vcd");
		$dumpvars(0,alu_tb);
		#1
		#2
		lhs_in = 8'h55;
		rhs_in = 8'hAA;
		operation = 4'hA; // AND

		#2 operation = 0;

		#2
		operation = 4'hB; // OR
		#2 operation = 0;
		

		#2
		operation = 4'h3; // add
		lhs_in = 200;
		rhs_in = 64;
		#2 operation = 0;

		#2
		operation = 4'h4; // addc
		lhs_in = 0;
		rhs_in = 0;
		#2 operation = 0;

		#2
		operation = 4'h4; // addc
		lhs_in = 0;
		rhs_in = 0;
		#2 operation = 0;


		#2
		operation = 4'h7; // sub
		lhs_in = 8'b00000001;
		rhs_in = 8'b10000001;
		#2 operation = 0;
        #10 $finish;
	end
endmodule

build/alu/alu_tb.vcd
$date
	Mon May 24 18:32:10 2021
$end
$version
	Icarus Verilog
$end
$timescale
	1ps
$end
$scope module alu_tb $end
$var wire 1 ! flag_zero $end
$var wire 1 " flag_sign $end
$var wire 1 # flag_overflow $end
$var wire 1 $ flag_lcarry $end
$var wire 1 % flag_acarry $end
$var wire 8 & bus_out [7:0] $end
$var wire 1 ' bus_en $end
$var reg 1 ( assert_bus $end
$var reg 1 ) clk $end
$var reg 8 * lhs_in [7:0] $end
$var reg 4 + operation [3:0] $end
$var reg 8 , rhs_in [7:0] $end
$scope module alu1 $end
$var wire 1 ( assert_bus $end
$var wire 1 ' bus_en $end
$var wire 1 ) clk $end
$var wire 1 $ flag_lcarry $end
$var wire 1 # flag_overflow $end
$var wire 8 - lhs_in [7:0] $end
$var wire 4 . operation [3:0] $end
$var wire 8 / rhs_in [7:0] $end
$var wire 8 0 rhs_out [7:0] $end
$var wire 9 1 result [8:0] $end
$var wire 8 2 lhs_out [7:0] $end
$var wire 1 3 lhs_carry_out $end
$var wire 1 ! flag_zero $end
$var wire 1 " flag_sign $end
$var wire 1 % flag_acarry $end
$var wire 1 4 carry $end
$var wire 8 5 bus_out [7:0] $end
$var wire 2 6 aluop_shift_select [1:0] $end
$var wire 4 7 aluop_logic_op [3:0] $end
$var wire 2 8 aluop_carry_select [1:0] $end
$var wire 1 9 alu_clk $end
$var reg 1 : lhs_carry_in $end
$var reg 1 ; prev_carry $end
$scope module alu_op1 $end
$var wire 1 9 alu_clk $end
$var wire 1 ) clk $end
$var wire 8 < current_op [7:0] $end
$var wire 4 = operation [3:0] $end
$var wire 2 > shift_select [1:0] $end
$var wire 1 ? select0 $end
$var wire 4 @ logic_op [3:0] $end
$var wire 2 A carry_select [1:0] $end
$upscope $end
$scope module lhs1 $end
$var wire 1 9 alu_clk $end
$var wire 1 : carry_in $end
$var wire 1 ) clk $end
$var wire 8 B in [7:0] $end
$var wire 2 C operation [1:0] $end
$var reg 1 3 carry_out $end
$var reg 8 D out [7:0] $end
$upscope $end
$scope module rhs1 $end
$var wire 1 9 alu_clk $end
$var wire 1 ) clk $end
$var wire 8 E lhs_in [7:0] $end
$var wire 4 F operation [3:0] $end
$var wire 8 G rhs_in [7:0] $end
$var reg 8 H out [7:0] $end
$upscope $end
$upscope $end
$upscope $end
$enddefinitions $end
#0
$dumpvars
b0 H
b0 G
b0 F
b0 E
b0 D
b0 C
b0 B
b0 A
b0 @
1?
b0 >
b0 =
b0 <
0;
0:
09
b0 8
b0 7
b0 6
b0 5
04
03
b0 2
b0 1
b0 0
b0 /
b0 .
b0 -
b0 ,
b0 +
b0 *
0)
x(
x'
b0 &
0%
0$
0#
0"
1!
$end
#1000
1)
#2000
0)
#3000
19
1)
b1000 7
b1000 @
b1000 F
b11 6
b11 >
b11 C
b111000 <
0?
b1010 +
b1010 .
b1010 =
b10101010 ,
b10101010 /
b10101010 G
b1010101 *
b1010101 -
b1010101 B
b1010101 E
#4000
09
0)
#5000
1)
b0 7
b0 @
b0 F
b0 6
b0 >
b0 C
b0 <
1?
b0 +
b0 .
b0 =
#6000
0)
#7000
b11111111 &
b11111111 5
0!
1"
b11111111 1
b11111111 0
b11111111 H
19
1)
b1110 7
b1110 @
b1110 F
b11 6
b11 >
b11 C
b111110 <
0?
b1011 +
b1011 .
b1011 =
#8000
09
0)
#9000
1)
b0 7
b0 @
b0 F
b0 6
b0 >
b0 C
b0 <
1?
b0 +
b0 .
b0 =
#10000
0)
#11000
1%
b1000 &
b1000 5
0"
b11001000 2
b11001000 D
b100001000 1
b1000000 0
b1000000 H
19
1)
b1100 7
b1100 @
b1100 F
b1000000 ,
b1000000 /
b1000000 G
b11001000 *
b11001000 -
b11001000 B
b11001000 E
b1100 <
0?
b11 +
b11 .
b11 =
#12000
09
0)
#13000
1)
b0 7
b0 @
b0 F
b0 <
1?
b0 +
b0 .
b0 =
#14000
0)
#15000
0%
b0 0
b0 H
b0 2
b0 D
b1 &
b1 5
b1 1
14
1;
19
1)
b1100 7
b1100 @
b1100 F
b1 8
b1 A
b0 ,
b0 /
b0 G
b0 *
b0 -
b0 B
b0 E
b1001100 <
0?
b100 +
b100 .
b100 =
#16000
09
0)
#17000
1)
b0 &
b0 5
1!
b0 1
04
b0 7
b0 @
b0 F
b0 8
b0 A
b0 <
1?
b0 +
b0 .
b0 =
#18000
0)
#19000
0;
19
1)
b0 &
b0 5
1!
b0 1
04
b1100 7
b1100 @
b1100 F
b1 8
b1 A
b1001100 <
0?
b100 +
b100 .
b100 =
#20000
09
0)
#21000
1)
b0 7
b0 @
b0 F
b0 8
b0 A
b0 <
1?
b0 +
b0 .
b0 =
#22000
0)
#23000
1#
1"
b1111110 0
b1111110 H
b1 2
b1 D
19
1)
b10000000 &
b10000000 5
0!
b10000000 1
14
b11 7
b11 @
b11 F
b10 8
b10 A
b10000001 ,
b10000001 /
b10000001 G
b1 *
b1 -
b1 B
b1 E
b10000011 <
0?
b111 +
b111 .
b111 =
#24000
09
0)
#25000
1)
0#
b1111111 &
b1111111 5
0"
b1111111 1
04
b0 7
b0 @
b0 F
b0 8
b0 A
b0 <
1?
b0 +
b0 .
b0 =
